lite_llm_json/__init__.py
lite_llm_json/lite_llm_json.py
lite_llm_json/test.py
LiteLLMJson-0.0.7.dist-info/METADATA
LiteLLMJson-0.0.7.dist-info/WHEEL
LiteLLMJson-0.0.7.dist-info/top_level.txt
LiteLLMJson-0.0.7.dist-info/RECORD
