Metadata-Version: 2.1
Name: LiteLLMJson
Version: 0.0.7
Summary: This library offers functionality to cleanly extract JSON from LLM responses and generate prompts for LLM that return JSON. It features a simple implementation while maintaining high versatility.
Home-page: https://github.com/HawkClaws/lite_llm_json
Author: HawkClaws
License: MIT
Project-URL: Source Code, https://github.com/HawkClaws/lite_llm_json
Requires-Python: >=3.6
Requires-Dist: jsonschema >=4.19.2
